joji/create_new_dataset.py
joji/jojify.py
joji/data/emoji_dict1.p
joji-1.2.0.dist-info/METADATA
joji-1.2.0.dist-info/WHEEL
joji-1.2.0.dist-info/top_level.txt
joji-1.2.0.dist-info/RECORD
