Metadata-Version: 2.1
Name: joji
Version: 1.2.0
Summary: convert a word to corresponding emoji
Home-page: https://github.com/GopikrishnanSasikumar/joji
Author: Gopikrishnan Sasikumar
Author-email: gopikrishnans1996@gmail.com
License: UNKNOWN
Keywords: text to emoji
Platform: UNKNOWN
Classifier: License :: OSI Approved :: BSD License
Classifier: Programming Language :: Python :: 3.5
Classifier: Programming Language :: Python :: 3.6
Classifier: Programming Language :: Python :: 3.7
Classifier: Programming Language :: Python :: 3.8
Requires-Dist: ipython
Requires-Dist: ipdb
Requires-Dist: pytest
Requires-Dist: requests
Requires-Dist: flask
Requires-Dist: gunicorn
Requires-Dist: sqlalchemy
Requires-Dist: mysql-connector-python
Requires-Dist: unidecode
Requires-Dist: spacy
Requires-Dist: emoji
Requires-Dist: numba
